{
  "updated_at": "2026-05-11T17:25:34Z",
  "items": [
    {
      "id": "fixed-event-20260512_022534",
      "kind": "event",
      "date": "2026-05-12",
      "created_at": "2026-05-11T17:25:34Z",
      "text": "うんこが土に吸い込まれていった。\n英訳: The poop sank into the soil.\nこれは唯一の例文とその英訳を提供しました。",
      "tweet": "うんこが土に吸い込まれていった。\n英訳: The poop sank into the soil.\nこれは唯一の例文とその英訳を提供しました。",
      "place": "",
      "links": [],
      "avatar_image": "image/avatar/normal.png",
      "permalink": "./posts/fixed-event-20260512_022534/index.html"
    }
  ]
}
